[
{"ImageContent":{"Description":"是否感觉需要补足整整一年的休息？今日图片上的这只北极狐懂你，它正窝在冰原岩石间，享受惬意时光。无论新年伴随寒风还是暖阳而来，请给自己五分钟，让身体舒展，再迎接接下来的365天。","Image":{"Url":"/th?id=OHR.NewYearFox_ZH-CN9312618796_1920x1080.webp","Wallpaper":"/th?id=OHR.NewYearFox_ZH-CN9312618796_1920x1200.jpg&rf=LaDigue_1920x1200.jpg","Downloadable":true},"Headline":"伸个懒腰，迈向新年！","Title":"正在睡觉的北极狐","Copyright":"© Chansak Joe/Getty Images","SocialGood":null,"MapLink":{"Url":"","Link":""},"QuickFact":{"MainText":"格里高利历在儒略历的基础上优化了闰年制度，让历法更精准，避免季节随时间逐渐错位。","LinkUrl":"","LinkText":""},"TriviaUrl":"/search?q=Bing+homepage+quiz&filters=WQOskey:\"HPQuiz_20260101_NewYearFox\"&FORM=HPQUIZ","BackstageUrl":"/search?q=%e5%85%83%e6%97%a6&form=hpcapt&filters=HpDate:\"20251231_1600\"+mgzv3configlist:\"BingQA_Encyclopedia_Layout\"","TriviaId":"HPQuiz_20260101_NewYearFox"},"Ssd":"20260101","Name":"NewYearFox","Market":"ZH-CN","Hash":"9312618796","FullDateString":"2026 1月 1","enddate":"20260101"},
{"ImageContent":{"Description":"从高空俯瞰威尼斯，宛如一幅迷人的水上画卷，但这座意大利瑰宝真正的魅力，藏在古老墙垣与曲折水巷之间。公元5世纪，它在潟湖中的一簇岛屿上诞生，由沼泽蜕变为海上霸主。中世纪时期，威尼斯成为连接欧洲与东方的重要贸易枢纽，财富与文化在此交织。如今，哥特式宫殿、文艺复兴艺术，以及圣马可大教堂、公爵宫、里亚托桥等地标，仍在诉说这座城市的辉煌历史。","Image":{"Url":"/th?id=OHR.VeniceView_ZH-CN3088407995_1920x1080.webp","Wallpaper":"/th?id=OHR.VeniceView_ZH-CN3088407995_1920x1200.jpg&rf=LaDigue_1920x1200.jpg","Downloadable":true},"Headline":"威尼斯的灵魂","Title":"威尼斯鸟瞰图, 意大利","Copyright":"© Clement Leonard/Getty Images","SocialGood":null,"MapLink":{"Url":"","Link":""},"QuickFact":{"MainText":"威尼斯的灵魂，古老而迷人，由118座岛屿织成水上锦图，400余座桥梁将它们串联。纵横的运河如脉络般流淌，贡多拉与船只穿梭不止，宛若一场永恒的奇迹。","LinkUrl":"","LinkText":""},"TriviaUrl":"/search?q=Bing+homepage+quiz&filters=WQOskey:\"HPQuiz_20260102_VeniceView\"&FORM=HPQUIZ","BackstageUrl":"/search?q=%e6%84%8f%e5%a4%a7%e5%88%a9%e5%a8%81%e5%b0%bc%e6%96%af&form=hpcapt&filters=HpDate:\"20260101_1600\"+mgzv3configlist:\"BingQA_Encyclopedia_Layout\"","TriviaId":"HPQuiz_20260102_VeniceView"},"Ssd":"20260102","Name":"VeniceView","Market":"ZH-CN","Hash":"3088407995","FullDateString":"2026 1月 2","enddate":"20260102"}
]